{
  "incumbent_ids": [
    2481
  ],
  "rejected_config_ids": [
    1,
    2,
    3,
    4,
    8,
    156,
    181,
    213,
    233,
    247,
    259,
    309,
    310,
    325,
    372,
    392,
    394,
    423,
    425,
    433,
    485,
    495,
    498,
    555,
    592,
    605,
    694,
    710,
    760,
    839,
    840,
    901,
    1016,
    1027,
    1065,
    1097,
    1190,
    1291,
    1373,
    1435,
    1450,
    1521,
    1574,
    1625,
    1627,
    1717,
    1778,
    1783,
    1819,
    1900,
    1915,
    1961,
    2199,
    2225,
    2234,
    2429,
    2453,
    2455,
    2476
  ],
  "incumbents_changed": 60,
  "trajectory": [
    {
      "config_ids": [
        1
      ],
      "costs": [
        4.516420350414451
      ],
      "trial": 1,
      "walltime": 0.060552120208740234
    },
    {
      "config_ids": [
        2
      ],
      "costs": [
        4.410900354174513
      ],
      "trial": 2,
      "walltime": 0.17395401000976562
    },
    {
      "config_ids": [
        3
      ],
      "costs": [
        4.090168080588584
      ],
      "trial": 3,
      "walltime": 0.2874777317047119
    },
    {
      "config_ids": [
        4
      ],
      "costs": [
        2.923521815483635
      ],
      "trial": 4,
      "walltime": 0.4060854911804199
    },
    {
      "config_ids": [
        8
      ],
      "costs": [
        1.4097550022320064
      ],
      "trial": 8,
      "walltime": 0.7134754657745361
    },
    {
      "config_ids": [
        156
      ],
      "costs": [
        1.1942940110519058
      ],
      "trial": 156,
      "walltime": 13.174839973449707
    },
    {
      "config_ids": [
        181
      ],
      "costs": [
        1.0617324700206818
      ],
      "trial": 181,
      "walltime": 18.317396879196167
    },
    {
      "config_ids": [
        213
      ],
      "costs": [
        0.961358937027797
      ],
      "trial": 213,
      "walltime": 26.864907264709473
    },
    {
      "config_ids": [
        233
      ],
      "costs": [
        0.9298390821430091
      ],
      "trial": 233,
      "walltime": 32.034523248672485
    },
    {
      "config_ids": [
        247
      ],
      "costs": [
        0.9035305259732214
      ],
      "trial": 247,
      "walltime": 36.90155506134033
    },
    {
      "config_ids": [
        259
      ],
      "costs": [
        0.8238263100371421
      ],
      "trial": 259,
      "walltime": 38.47309875488281
    },
    {
      "config_ids": [
        309
      ],
      "costs": [
        0.8131025071309592
      ],
      "trial": 309,
      "walltime": 55.34790253639221
    },
    {
      "config_ids": [
        310
      ],
      "costs": [
        0.7537318356936241
      ],
      "trial": 310,
      "walltime": 55.544201612472534
    },
    {
      "config_ids": [
        325
      ],
      "costs": [
        0.6748309904823213
      ],
      "trial": 325,
      "walltime": 60.44330406188965
    },
    {
      "config_ids": [
        372
      ],
      "costs": [
        0.6442747754656183
      ],
      "trial": 372,
      "walltime": 73.66359806060791
    },
    {
      "config_ids": [
        392
      ],
      "costs": [
        0.6387191791985092
      ],
      "trial": 392,
      "walltime": 82.53199887275696
    },
    {
      "config_ids": [
        394
      ],
      "costs": [
        0.6184786399583773
      ],
      "trial": 394,
      "walltime": 82.90747213363647
    },
    {
      "config_ids": [
        423
      ],
      "costs": [
        0.6173036071051586
      ],
      "trial": 423,
      "walltime": 93.67924451828003
    },
    {
      "config_ids": [
        425
      ],
      "costs": [
        0.6043545701463673
      ],
      "trial": 425,
      "walltime": 94.09718227386475
    },
    {
      "config_ids": [
        433
      ],
      "costs": [
        0.5889745917730939
      ],
      "trial": 433,
      "walltime": 95.58082342147827
    },
    {
      "config_ids": [
        485
      ],
      "costs": [
        0.5869856299067197
      ],
      "trial": 485,
      "walltime": 116.90209364891052
    },
    {
      "config_ids": [
        495
      ],
      "costs": [
        0.5750098940503088
      ],
      "trial": 495,
      "walltime": 118.86726450920105
    },
    {
      "config_ids": [
        498
      ],
      "costs": [
        0.572137892630879
      ],
      "trial": 498,
      "walltime": 119.4780662059784
    },
    {
      "config_ids": [
        555
      ],
      "costs": [
        0.5706793421487037
      ],
      "trial": 555,
      "walltime": 143.36696577072144
    },
    {
      "config_ids": [
        592
      ],
      "costs": [
        0.5686438111290423
      ],
      "trial": 592,
      "walltime": 157.9243288040161
    },
    {
      "config_ids": [
        605
      ],
      "costs": [
        0.566559114621984
      ],
      "trial": 605,
      "walltime": 164.46589398384094
    },
    {
      "config_ids": [
        694
      ],
      "costs": [
        0.562636423945596
      ],
      "trial": 694,
      "walltime": 203.47276329994202
    },
    {
      "config_ids": [
        710
      ],
      "costs": [
        0.5569854099729852
      ],
      "trial": 710,
      "walltime": 210.77176713943481
    },
    {
      "config_ids": [
        760
      ],
      "costs": [
        0.5533561097486542
      ],
      "trial": 760,
      "walltime": 234.06762385368347
    },
    {
      "config_ids": [
        839
      ],
      "costs": [
        0.5532762404825791
      ],
      "trial": 839,
      "walltime": 272.3798887729645
    },
    {
      "config_ids": [
        840
      ],
      "costs": [
        0.5527215736977061
      ],
      "trial": 840,
      "walltime": 272.7107980251312
    },
    {
      "config_ids": [
        901
      ],
      "costs": [
        0.5519188063485538
      ],
      "trial": 901,
      "walltime": 303.9931962490082
    },
    {
      "config_ids": [
        1016
      ],
      "costs": [
        0.5514653620444927
      ],
      "trial": 1016,
      "walltime": 366.0235447883606
    },
    {
      "config_ids": [
        1027
      ],
      "costs": [
        0.5514436278336681
      ],
      "trial": 1027,
      "walltime": 369.7007746696472
    },
    {
      "config_ids": [
        1065
      ],
      "costs": [
        0.5514421537327707
      ],
      "trial": 1065,
      "walltime": 393.9174425601959
    },
    {
      "config_ids": [
        1097
      ],
      "costs": [
        0.5511755414960391
      ],
      "trial": 1097,
      "walltime": 412.69684624671936
    },
    {
      "config_ids": [
        1190
      ],
      "costs": [
        0.55092948370244
      ],
      "trial": 1190,
      "walltime": 470.97263503074646
    },
    {
      "config_ids": [
        1291
      ],
      "costs": [
        0.5509220191152778
      ],
      "trial": 1291,
      "walltime": 535.1857824325562
    },
    {
      "config_ids": [
        1373
      ],
      "costs": [
        0.5507978142681467
      ],
      "trial": 1373,
      "walltime": 589.7329063415527
    },
    {
      "config_ids": [
        1435
      ],
      "costs": [
        0.5507090249258576
      ],
      "trial": 1435,
      "walltime": 633.9257130622864
    },
    {
      "config_ids": [
        1450
      ],
      "costs": [
        0.55057243462202
      ],
      "trial": 1450,
      "walltime": 644.4459571838379
    },
    {
      "config_ids": [
        1521
      ],
      "costs": [
        0.5505392888162395
      ],
      "trial": 1521,
      "walltime": 693.6610369682312
    },
    {
      "config_ids": [
        1574
      ],
      "costs": [
        0.5504359433000513
      ],
      "trial": 1574,
      "walltime": 735.3761601448059
    },
    {
      "config_ids": [
        1625
      ],
      "costs": [
        0.5503834418522902
      ],
      "trial": 1625,
      "walltime": 773.1305484771729
    },
    {
      "config_ids": [
        1627
      ],
      "costs": [
        0.5497348843208777
      ],
      "trial": 1627,
      "walltime": 774.1487069129944
    },
    {
      "config_ids": [
        1717
      ],
      "costs": [
        0.5494877241308774
      ],
      "trial": 1717,
      "walltime": 843.6724014282227
    },
    {
      "config_ids": [
        1778
      ],
      "costs": [
        0.5492767582068919
      ],
      "trial": 1778,
      "walltime": 884.646810054779
    },
    {
      "config_ids": [
        1783
      ],
      "costs": [
        0.5491213760761156
      ],
      "trial": 1783,
      "walltime": 892.0187222957611
    },
    {
      "config_ids": [
        1819
      ],
      "costs": [
        0.5490765954345626
      ],
      "trial": 1819,
      "walltime": 920.3960750102997
    },
    {
      "config_ids": [
        1900
      ],
      "costs": [
        0.5487990880401987
      ],
      "trial": 1900,
      "walltime": 987.1911978721619
    },
    {
      "config_ids": [
        1915
      ],
      "costs": [
        0.5487971101346482
      ],
      "trial": 1915,
      "walltime": 999.8817799091339
    },
    {
      "config_ids": [
        1961
      ],
      "costs": [
        0.5484418697612099
      ],
      "trial": 1961,
      "walltime": 1040.3016049861908
    },
    {
      "config_ids": [
        2199
      ],
      "costs": [
        0.5484083378028686
      ],
      "trial": 2199,
      "walltime": 1260.0561685562134
    },
    {
      "config_ids": [
        2225
      ],
      "costs": [
        0.5483505595533374
      ],
      "trial": 2225,
      "walltime": 1282.0576627254486
    },
    {
      "config_ids": [
        2234
      ],
      "costs": [
        0.5482525782763706
      ],
      "trial": 2234,
      "walltime": 1293.4306559562683
    },
    {
      "config_ids": [
        2429
      ],
      "costs": [
        0.5482291674127999
      ],
      "trial": 2429,
      "walltime": 1488.6270840168
    },
    {
      "config_ids": [
        2453
      ],
      "costs": [
        0.5482009111360189
      ],
      "trial": 2453,
      "walltime": 1516.3747873306274
    },
    {
      "config_ids": [
        2455
      ],
      "costs": [
        0.5481883716363853
      ],
      "trial": 2455,
      "walltime": 1517.799354314804
    },
    {
      "config_ids": [
        2476
      ],
      "costs": [
        0.5481865059226968
      ],
      "trial": 2476,
      "walltime": 1538.4466350078583
    },
    {
      "config_ids": [
        2481
      ],
      "costs": [
        0.548175702135721
      ],
      "trial": 2481,
      "walltime": 1541.962736606598
    }
  ],
  "state": {
    "queue": [
      [
        2500,
        1
      ]
    ]
  }
}