{
  "incumbent_ids": [
    875
  ],
  "rejected_config_ids": [
    1,
    2,
    15,
    18,
    79,
    143,
    178,
    181,
    182,
    183,
    193,
    194,
    213,
    214,
    218,
    223,
    246,
    249,
    257,
    285,
    310,
    311,
    314,
    316,
    321,
    329,
    453,
    527,
    549,
    587,
    700,
    710,
    765,
    794
  ],
  "incumbents_changed": 35,
  "trajectory": [
    {
      "config_ids": [
        1
      ],
      "costs": [
        8.848522966978132
      ],
      "trial": 1,
      "walltime": 0.02553415298461914
    },
    {
      "config_ids": [
        2
      ],
      "costs": [
        0.9349629718417966
      ],
      "trial": 2,
      "walltime": 0.07394552230834961
    },
    {
      "config_ids": [
        15
      ],
      "costs": [
        0.39613279251569916
      ],
      "trial": 15,
      "walltime": 0.6152544021606445
    },
    {
      "config_ids": [
        18
      ],
      "costs": [
        0.21071557776841116
      ],
      "trial": 18,
      "walltime": 0.7276175022125244
    },
    {
      "config_ids": [
        79
      ],
      "costs": [
        0.13080935362941576
      ],
      "trial": 79,
      "walltime": 3.3426191806793213
    },
    {
      "config_ids": [
        143
      ],
      "costs": [
        0.12288154016185768
      ],
      "trial": 143,
      "walltime": 6.260973930358887
    },
    {
      "config_ids": [
        178
      ],
      "costs": [
        0.08368477204174733
      ],
      "trial": 178,
      "walltime": 8.131313800811768
    },
    {
      "config_ids": [
        181
      ],
      "costs": [
        0.07739168211590333
      ],
      "trial": 181,
      "walltime": 8.991978883743286
    },
    {
      "config_ids": [
        182
      ],
      "costs": [
        0.04363414406214219
      ],
      "trial": 182,
      "walltime": 9.068384885787964
    },
    {
      "config_ids": [
        183
      ],
      "costs": [
        0.01915929826512132
      ],
      "trial": 183,
      "walltime": 9.143975019454956
    },
    {
      "config_ids": [
        193
      ],
      "costs": [
        0.014556138619504945
      ],
      "trial": 193,
      "walltime": 9.738686800003052
    },
    {
      "config_ids": [
        194
      ],
      "costs": [
        0.010368295704432592
      ],
      "trial": 194,
      "walltime": 9.817625284194946
    },
    {
      "config_ids": [
        213
      ],
      "costs": [
        0.010348774417846589
      ],
      "trial": 213,
      "walltime": 12.355290651321411
    },
    {
      "config_ids": [
        214
      ],
      "costs": [
        0.00933997993158195
      ],
      "trial": 214,
      "walltime": 12.436412811279297
    },
    {
      "config_ids": [
        218
      ],
      "costs": [
        0.00852356248271678
      ],
      "trial": 218,
      "walltime": 12.706627607345581
    },
    {
      "config_ids": [
        223
      ],
      "costs": [
        0.00832863711917029
      ],
      "trial": 223,
      "walltime": 13.043095588684082
    },
    {
      "config_ids": [
        246
      ],
      "costs": [
        0.008289021384802546
      ],
      "trial": 246,
      "walltime": 17.504488706588745
    },
    {
      "config_ids": [
        249
      ],
      "costs": [
        0.006237213460248949
      ],
      "trial": 249,
      "walltime": 17.854848623275757
    },
    {
      "config_ids": [
        257
      ],
      "costs": [
        0.004048133085851522
      ],
      "trial": 257,
      "walltime": 18.723517417907715
    },
    {
      "config_ids": [
        285
      ],
      "costs": [
        0.0038705826648353283
      ],
      "trial": 285,
      "walltime": 23.782450437545776
    },
    {
      "config_ids": [
        310
      ],
      "costs": [
        0.003305221541129749
      ],
      "trial": 310,
      "walltime": 27.262706995010376
    },
    {
      "config_ids": [
        311
      ],
      "costs": [
        0.0030735704288354553
      ],
      "trial": 311,
      "walltime": 27.36169695854187
    },
    {
      "config_ids": [
        314
      ],
      "costs": [
        0.0027859145216045382
      ],
      "trial": 314,
      "walltime": 27.61868405342102
    },
    {
      "config_ids": [
        316
      ],
      "costs": [
        0.002779326309146543
      ],
      "trial": 316,
      "walltime": 27.799638748168945
    },
    {
      "config_ids": [
        321
      ],
      "costs": [
        0.0013559645864635133
      ],
      "trial": 321,
      "walltime": 28.227177143096924
    },
    {
      "config_ids": [
        329
      ],
      "costs": [
        2.8826372006804255e-05
      ],
      "trial": 329,
      "walltime": 29.74805474281311
    },
    {
      "config_ids": [
        453
      ],
      "costs": [
        2.881624978818465e-05
      ],
      "trial": 453,
      "walltime": 48.15998935699463
    },
    {
      "config_ids": [
        527
      ],
      "costs": [
        7.139618702821677e-06
      ],
      "trial": 527,
      "walltime": 59.38784694671631
    },
    {
      "config_ids": [
        549
      ],
      "costs": [
        6.798362137412232e-06
      ],
      "trial": 549,
      "walltime": 63.91122245788574
    },
    {
      "config_ids": [
        587
      ],
      "costs": [
        6.131100879289234e-06
      ],
      "trial": 587,
      "walltime": 70.78331708908081
    },
    {
      "config_ids": [
        700
      ],
      "costs": [
        5.492531765087561e-06
      ],
      "trial": 700,
      "walltime": 94.01851153373718
    },
    {
      "config_ids": [
        710
      ],
      "costs": [
        5.360397894389911e-06
      ],
      "trial": 710,
      "walltime": 96.59769988059998
    },
    {
      "config_ids": [
        765
      ],
      "costs": [
        5.322237253515922e-06
      ],
      "trial": 765,
      "walltime": 108.5545301437378
    },
    {
      "config_ids": [
        794
      ],
      "costs": [
        5.147975191804787e-06
      ],
      "trial": 794,
      "walltime": 117.34712290763855
    },
    {
      "config_ids": [
        875
      ],
      "costs": [
        5.082588687396846e-06
      ],
      "trial": 875,
      "walltime": 137.97965574264526
    }
  ],
  "state": {
    "queue": []
  }
}