{
  "incumbent_ids": [
    2314
  ],
  "rejected_config_ids": [
    1,
    2,
    3,
    4,
    8,
    156,
    204,
    216,
    226,
    246,
    259,
    270,
    328,
    332,
    342,
    407,
    411,
    454,
    465,
    517,
    533,
    550,
    576,
    605,
    613,
    619,
    653,
    677,
    678,
    681,
    697,
    710,
    712,
    746,
    762,
    799,
    808,
    904,
    905,
    969,
    1011,
    1127,
    1157,
    1285,
    1320,
    1430,
    1649,
    1685,
    1693,
    1705,
    1717,
    1847,
    1857,
    1898,
    1901,
    2205,
    2267,
    2280
  ],
  "incumbents_changed": 59,
  "trajectory": [
    {
      "config_ids": [
        1
      ],
      "costs": [
        4.55795889034563
      ],
      "trial": 1,
      "walltime": 0.06160926818847656
    },
    {
      "config_ids": [
        2
      ],
      "costs": [
        4.428030384056163
      ],
      "trial": 2,
      "walltime": 0.177581787109375
    },
    {
      "config_ids": [
        3
      ],
      "costs": [
        4.162958673440653
      ],
      "trial": 3,
      "walltime": 0.2936379909515381
    },
    {
      "config_ids": [
        4
      ],
      "costs": [
        2.8904781086764197
      ],
      "trial": 4,
      "walltime": 0.41046929359436035
    },
    {
      "config_ids": [
        8
      ],
      "costs": [
        1.377816495670487
      ],
      "trial": 8,
      "walltime": 0.7170357704162598
    },
    {
      "config_ids": [
        156
      ],
      "costs": [
        1.1586938573387473
      ],
      "trial": 156,
      "walltime": 13.277563095092773
    },
    {
      "config_ids": [
        204
      ],
      "costs": [
        1.096701307103859
      ],
      "trial": 204,
      "walltime": 22.519726037979126
    },
    {
      "config_ids": [
        216
      ],
      "costs": [
        1.0681613068944396
      ],
      "trial": 216,
      "walltime": 26.389492988586426
    },
    {
      "config_ids": [
        226
      ],
      "costs": [
        0.9871423748577791
      ],
      "trial": 226,
      "walltime": 27.64685869216919
    },
    {
      "config_ids": [
        246
      ],
      "costs": [
        0.8832607436318637
      ],
      "trial": 246,
      "walltime": 35.107380390167236
    },
    {
      "config_ids": [
        259
      ],
      "costs": [
        0.7806318179010657
      ],
      "trial": 259,
      "walltime": 36.77857565879822
    },
    {
      "config_ids": [
        270
      ],
      "costs": [
        0.7784194545206584
      ],
      "trial": 270,
      "walltime": 40.71312499046326
    },
    {
      "config_ids": [
        328
      ],
      "costs": [
        0.7585273373779934
      ],
      "trial": 328,
      "walltime": 58.814584732055664
    },
    {
      "config_ids": [
        332
      ],
      "costs": [
        0.695634483224791
      ],
      "trial": 332,
      "walltime": 59.43303894996643
    },
    {
      "config_ids": [
        342
      ],
      "costs": [
        0.5810377694447628
      ],
      "trial": 342,
      "walltime": 63.7096586227417
    },
    {
      "config_ids": [
        407
      ],
      "costs": [
        0.5714944800452716
      ],
      "trial": 407,
      "walltime": 84.97228336334229
    },
    {
      "config_ids": [
        411
      ],
      "costs": [
        0.559285766675779
      ],
      "trial": 411,
      "walltime": 85.69301795959473
    },
    {
      "config_ids": [
        454
      ],
      "costs": [
        0.5509806831570959
      ],
      "trial": 454,
      "walltime": 102.29296112060547
    },
    {
      "config_ids": [
        465
      ],
      "costs": [
        0.5478881146285379
      ],
      "trial": 465,
      "walltime": 104.33134937286377
    },
    {
      "config_ids": [
        517
      ],
      "costs": [
        0.5447526851457275
      ],
      "trial": 517,
      "walltime": 124.97935628890991
    },
    {
      "config_ids": [
        533
      ],
      "costs": [
        0.5427990112696234
      ],
      "trial": 533,
      "walltime": 133.1334364414215
    },
    {
      "config_ids": [
        550
      ],
      "costs": [
        0.5427131313300061
      ],
      "trial": 550,
      "walltime": 140.37078762054443
    },
    {
      "config_ids": [
        576
      ],
      "costs": [
        0.5423688068873408
      ],
      "trial": 576,
      "walltime": 148.9993543624878
    },
    {
      "config_ids": [
        605
      ],
      "costs": [
        0.5420887224033628
      ],
      "trial": 605,
      "walltime": 163.43578243255615
    },
    {
      "config_ids": [
        613
      ],
      "costs": [
        0.5401516006998879
      ],
      "trial": 613,
      "walltime": 168.3968403339386
    },
    {
      "config_ids": [
        619
      ],
      "costs": [
        0.5376843262688122
      ],
      "trial": 619,
      "walltime": 169.7090299129486
    },
    {
      "config_ids": [
        653
      ],
      "costs": [
        0.5360803917084311
      ],
      "trial": 653,
      "walltime": 183.55407762527466
    },
    {
      "config_ids": [
        677
      ],
      "costs": [
        0.5359188469424965
      ],
      "trial": 677,
      "walltime": 198.96590089797974
    },
    {
      "config_ids": [
        678
      ],
      "costs": [
        0.5350632510695656
      ],
      "trial": 678,
      "walltime": 199.3618106842041
    },
    {
      "config_ids": [
        681
      ],
      "costs": [
        0.5344606035566876
      ],
      "trial": 681,
      "walltime": 200.2749376296997
    },
    {
      "config_ids": [
        697
      ],
      "costs": [
        0.5339140672457362
      ],
      "trial": 697,
      "walltime": 207.09523677825928
    },
    {
      "config_ids": [
        710
      ],
      "costs": [
        0.5318097679852434
      ],
      "trial": 710,
      "walltime": 213.3242802619934
    },
    {
      "config_ids": [
        712
      ],
      "costs": [
        0.531237277362725
      ],
      "trial": 712,
      "walltime": 213.86772418022156
    },
    {
      "config_ids": [
        746
      ],
      "costs": [
        0.5306008639680821
      ],
      "trial": 746,
      "walltime": 228.85107851028442
    },
    {
      "config_ids": [
        762
      ],
      "costs": [
        0.5304499186940517
      ],
      "trial": 762,
      "walltime": 237.62330293655396
    },
    {
      "config_ids": [
        799
      ],
      "costs": [
        0.5303681000280086
      ],
      "trial": 799,
      "walltime": 255.44226956367493
    },
    {
      "config_ids": [
        808
      ],
      "costs": [
        0.5301006463988306
      ],
      "trial": 808,
      "walltime": 262.1381747722626
    },
    {
      "config_ids": [
        904
      ],
      "costs": [
        0.5291858262956693
      ],
      "trial": 904,
      "walltime": 310.53194856643677
    },
    {
      "config_ids": [
        905
      ],
      "costs": [
        0.5284369560062864
      ],
      "trial": 905,
      "walltime": 310.8850381374359
    },
    {
      "config_ids": [
        969
      ],
      "costs": [
        0.5284219208109457
      ],
      "trial": 969,
      "walltime": 345.1893095970154
    },
    {
      "config_ids": [
        1011
      ],
      "costs": [
        0.5282438046496795
      ],
      "trial": 1011,
      "walltime": 366.75707387924194
    },
    {
      "config_ids": [
        1127
      ],
      "costs": [
        0.5276295411141891
      ],
      "trial": 1127,
      "walltime": 435.1608169078827
    },
    {
      "config_ids": [
        1157
      ],
      "costs": [
        0.5272493895300633
      ],
      "trial": 1157,
      "walltime": 453.8801691532135
    },
    {
      "config_ids": [
        1285
      ],
      "costs": [
        0.5271233286481096
      ],
      "trial": 1285,
      "walltime": 533.1251993179321
    },
    {
      "config_ids": [
        1320
      ],
      "costs": [
        0.526823989477404
      ],
      "trial": 1320,
      "walltime": 555.6096522808075
    },
    {
      "config_ids": [
        1430
      ],
      "costs": [
        0.5263379252593318
      ],
      "trial": 1430,
      "walltime": 631.4064431190491
    },
    {
      "config_ids": [
        1649
      ],
      "costs": [
        0.5262811534096478
      ],
      "trial": 1649,
      "walltime": 792.6098594665527
    },
    {
      "config_ids": [
        1685
      ],
      "costs": [
        0.5262353192723374
      ],
      "trial": 1685,
      "walltime": 837.2589881420135
    },
    {
      "config_ids": [
        1693
      ],
      "costs": [
        0.52621947242064
      ],
      "trial": 1693,
      "walltime": 841.3112778663635
    },
    {
      "config_ids": [
        1705
      ],
      "costs": [
        0.5261543894011076
      ],
      "trial": 1705,
      "walltime": 851.8994870185852
    },
    {
      "config_ids": [
        1717
      ],
      "costs": [
        0.5261427980979728
      ],
      "trial": 1717,
      "walltime": 863.1468977928162
    },
    {
      "config_ids": [
        1847
      ],
      "costs": [
        0.526120231834294
      ],
      "trial": 1847,
      "walltime": 970.0909421443939
    },
    {
      "config_ids": [
        1857
      ],
      "costs": [
        0.526098865576665
      ],
      "trial": 1857,
      "walltime": 975.4321582317352
    },
    {
      "config_ids": [
        1898
      ],
      "costs": [
        0.5260804071329879
      ],
      "trial": 1898,
      "walltime": 1012.3952984809875
    },
    {
      "config_ids": [
        1901
      ],
      "costs": [
        0.5260115996467664
      ],
      "trial": 1901,
      "walltime": 1014.0807466506958
    },
    {
      "config_ids": [
        2205
      ],
      "costs": [
        0.5259916939329692
      ],
      "trial": 2205,
      "walltime": 1298.5306437015533
    },
    {
      "config_ids": [
        2267
      ],
      "costs": [
        0.5259453222291217
      ],
      "trial": 2267,
      "walltime": 1365.407014131546
    },
    {
      "config_ids": [
        2280
      ],
      "costs": [
        0.5258421189217379
      ],
      "trial": 2280,
      "walltime": 1378.929396390915
    },
    {
      "config_ids": [
        2314
      ],
      "costs": [
        0.5256748363837975
      ],
      "trial": 2314,
      "walltime": 1411.9013154506683
    }
  ],
  "state": {
    "queue": [
      [
        2500,
        1
      ]
    ]
  }
}