{
  "incumbent_ids": [
    2445
  ],
  "rejected_config_ids": [
    1,
    2,
    34,
    127,
    185,
    186,
    198,
    199,
    203,
    232,
    246,
    249,
    251,
    279,
    281,
    282,
    284,
    293,
    294,
    306,
    310,
    323,
    346,
    348,
    349,
    403,
    472,
    482,
    521,
    539,
    619,
    690,
    694,
    923,
    981,
    989,
    1018,
    1077,
    1078,
    1205,
    1320,
    1372,
    1429,
    1445,
    1446,
    1447,
    1493,
    1527,
    1544,
    1637,
    1638,
    1685,
    1882,
    1893,
    1895,
    1898,
    2229,
    2342
  ],
  "incumbents_changed": 59,
  "trajectory": [
    {
      "config_ids": [
        1
      ],
      "costs": [
        8.855663874641515
      ],
      "trial": 1,
      "walltime": 0.03972005844116211
    },
    {
      "config_ids": [
        2
      ],
      "costs": [
        0.2847734669959755
      ],
      "trial": 2,
      "walltime": 0.1180720329284668
    },
    {
      "config_ids": [
        34
      ],
      "costs": [
        0.17496804802783997
      ],
      "trial": 34,
      "walltime": 1.588383674621582
    },
    {
      "config_ids": [
        127
      ],
      "costs": [
        0.08277586021368755
      ],
      "trial": 127,
      "walltime": 5.294720888137817
    },
    {
      "config_ids": [
        185
      ],
      "costs": [
        0.053304260305107716
      ],
      "trial": 185,
      "walltime": 8.827646255493164
    },
    {
      "config_ids": [
        186
      ],
      "costs": [
        0.03277408128351781
      ],
      "trial": 186,
      "walltime": 8.903012990951538
    },
    {
      "config_ids": [
        198
      ],
      "costs": [
        0.022764746729049587
      ],
      "trial": 198,
      "walltime": 10.26128602027893
    },
    {
      "config_ids": [
        199
      ],
      "costs": [
        0.013581033130554223
      ],
      "trial": 199,
      "walltime": 10.339695453643799
    },
    {
      "config_ids": [
        203
      ],
      "costs": [
        0.011934345138764804
      ],
      "trial": 203,
      "walltime": 10.595649480819702
    },
    {
      "config_ids": [
        232
      ],
      "costs": [
        0.011726229848435233
      ],
      "trial": 232,
      "walltime": 13.807148694992065
    },
    {
      "config_ids": [
        246
      ],
      "costs": [
        0.011245146269536205
      ],
      "trial": 246,
      "walltime": 15.441836595535278
    },
    {
      "config_ids": [
        249
      ],
      "costs": [
        0.011109966065709817
      ],
      "trial": 249,
      "walltime": 15.660925149917603
    },
    {
      "config_ids": [
        251
      ],
      "costs": [
        0.010569048259820996
      ],
      "trial": 251,
      "walltime": 15.815932750701904
    },
    {
      "config_ids": [
        279
      ],
      "costs": [
        0.008749960295927426
      ],
      "trial": 279,
      "walltime": 19.127793312072754
    },
    {
      "config_ids": [
        281
      ],
      "costs": [
        0.006878890965803658
      ],
      "trial": 281,
      "walltime": 19.287385940551758
    },
    {
      "config_ids": [
        282
      ],
      "costs": [
        0.006557347663648376
      ],
      "trial": 282,
      "walltime": 19.37755060195923
    },
    {
      "config_ids": [
        284
      ],
      "costs": [
        0.0053945739117263435
      ],
      "trial": 284,
      "walltime": 19.543750047683716
    },
    {
      "config_ids": [
        293
      ],
      "costs": [
        0.004686691085573282
      ],
      "trial": 293,
      "walltime": 21.38392996788025
    },
    {
      "config_ids": [
        294
      ],
      "costs": [
        0.003999777683360209
      ],
      "trial": 294,
      "walltime": 21.536022901535034
    },
    {
      "config_ids": [
        306
      ],
      "costs": [
        0.0031250257393824424
      ],
      "trial": 306,
      "walltime": 22.956257343292236
    },
    {
      "config_ids": [
        310
      ],
      "costs": [
        0.002521681287145851
      ],
      "trial": 310,
      "walltime": 24.716630220413208
    },
    {
      "config_ids": [
        323
      ],
      "costs": [
        0.0016680636948981243
      ],
      "trial": 323,
      "walltime": 26.360838651657104
    },
    {
      "config_ids": [
        346
      ],
      "costs": [
        0.001495857894420078
      ],
      "trial": 346,
      "walltime": 32.077327728271484
    },
    {
      "config_ids": [
        348
      ],
      "costs": [
        0.001115632547895295
      ],
      "trial": 348,
      "walltime": 32.375732421875
    },
    {
      "config_ids": [
        349
      ],
      "costs": [
        0.0008892709098562996
      ],
      "trial": 349,
      "walltime": 32.538310050964355
    },
    {
      "config_ids": [
        403
      ],
      "costs": [
        0.0008814774373031534
      ],
      "trial": 403,
      "walltime": 43.47836756706238
    },
    {
      "config_ids": [
        472
      ],
      "costs": [
        0.0008631935331320321
      ],
      "trial": 472,
      "walltime": 57.66599798202515
    },
    {
      "config_ids": [
        482
      ],
      "costs": [
        0.0008524549897064144
      ],
      "trial": 482,
      "walltime": 58.73798584938049
    },
    {
      "config_ids": [
        521
      ],
      "costs": [
        0.0006252164786547279
      ],
      "trial": 521,
      "walltime": 65.57466721534729
    },
    {
      "config_ids": [
        539
      ],
      "costs": [
        0.000625144912759546
      ],
      "trial": 539,
      "walltime": 68.56047773361206
    },
    {
      "config_ids": [
        619
      ],
      "costs": [
        0.0006247197784378141
      ],
      "trial": 619,
      "walltime": 83.30986881256104
    },
    {
      "config_ids": [
        690
      ],
      "costs": [
        0.0006241241747231543
      ],
      "trial": 690,
      "walltime": 97.1429431438446
    },
    {
      "config_ids": [
        694
      ],
      "costs": [
        0.00062336064499499
      ],
      "trial": 694,
      "walltime": 98.84242701530457
    },
    {
      "config_ids": [
        923
      ],
      "costs": [
        0.000577033908994993
      ],
      "trial": 923,
      "walltime": 155.58622431755066
    },
    {
      "config_ids": [
        981
      ],
      "costs": [
        0.0005769316431886136
      ],
      "trial": 981,
      "walltime": 177.9700222015381
    },
    {
      "config_ids": [
        989
      ],
      "costs": [
        0.0005765680316578547
      ],
      "trial": 989,
      "walltime": 179.46166563034058
    },
    {
      "config_ids": [
        1018
      ],
      "costs": [
        0.0005759728001043082
      ],
      "trial": 1018,
      "walltime": 187.55038928985596
    },
    {
      "config_ids": [
        1077
      ],
      "costs": [
        0.0005717790434868375
      ],
      "trial": 1077,
      "walltime": 205.1337764263153
    },
    {
      "config_ids": [
        1078
      ],
      "costs": [
        0.0005716135096114616
      ],
      "trial": 1078,
      "walltime": 205.35127973556519
    },
    {
      "config_ids": [
        1205
      ],
      "costs": [
        0.0005688494789225697
      ],
      "trial": 1205,
      "walltime": 245.5696246623993
    },
    {
      "config_ids": [
        1320
      ],
      "costs": [
        0.0005685188617067057
      ],
      "trial": 1320,
      "walltime": 285.4674038887024
    },
    {
      "config_ids": [
        1372
      ],
      "costs": [
        0.000563251740785388
      ],
      "trial": 1372,
      "walltime": 308.3724808692932
    },
    {
      "config_ids": [
        1429
      ],
      "costs": [
        0.0005616833976875247
      ],
      "trial": 1429,
      "walltime": 330.6070897579193
    },
    {
      "config_ids": [
        1445
      ],
      "costs": [
        0.0005615946256957056
      ],
      "trial": 1445,
      "walltime": 337.1479947566986
    },
    {
      "config_ids": [
        1446
      ],
      "costs": [
        0.0005615802332756035
      ],
      "trial": 1446,
      "walltime": 337.4209678173065
    },
    {
      "config_ids": [
        1447
      ],
      "costs": [
        0.0005615622459923542
      ],
      "trial": 1447,
      "walltime": 337.6925935745239
    },
    {
      "config_ids": [
        1493
      ],
      "costs": [
        0.0005612014547094362
      ],
      "trial": 1493,
      "walltime": 358.13579273223877
    },
    {
      "config_ids": [
        1527
      ],
      "costs": [
        0.0005604114982782793
      ],
      "trial": 1527,
      "walltime": 373.6307141780853
    },
    {
      "config_ids": [
        1544
      ],
      "costs": [
        0.0005602654154354711
      ],
      "trial": 1544,
      "walltime": 380.63661909103394
    },
    {
      "config_ids": [
        1637
      ],
      "costs": [
        0.0005601532538931929
      ],
      "trial": 1637,
      "walltime": 421.1252918243408
    },
    {
      "config_ids": [
        1638
      ],
      "costs": [
        0.0005601006287205711
      ],
      "trial": 1638,
      "walltime": 421.4294521808624
    },
    {
      "config_ids": [
        1685
      ],
      "costs": [
        0.0005599545748336831
      ],
      "trial": 1685,
      "walltime": 441.7620837688446
    },
    {
      "config_ids": [
        1882
      ],
      "costs": [
        0.0005599531609108062
      ],
      "trial": 1882,
      "walltime": 536.0330016613007
    },
    {
      "config_ids": [
        1893
      ],
      "costs": [
        0.0005599428697860872
      ],
      "trial": 1893,
      "walltime": 544.3973786830902
    },
    {
      "config_ids": [
        1895
      ],
      "costs": [
        0.0005594585207323287
      ],
      "trial": 1895,
      "walltime": 545.4479494094849
    },
    {
      "config_ids": [
        1898
      ],
      "costs": [
        0.0005594245160958035
      ],
      "trial": 1898,
      "walltime": 547.6562843322754
    },
    {
      "config_ids": [
        2229
      ],
      "costs": [
        0.000559406303709791
      ],
      "trial": 2229,
      "walltime": 780.3997223377228
    },
    {
      "config_ids": [
        2342
      ],
      "costs": [
        0.0005593883783800854
      ],
      "trial": 2342,
      "walltime": 882.1763775348663
    },
    {
      "config_ids": [
        2445
      ],
      "costs": [
        0.0005587979295168454
      ],
      "trial": 2445,
      "walltime": 971.8426351547241
    }
  ],
  "state": {
    "queue": [
      [
        2500,
        1
      ]
    ]
  }
}